{
  "id": "12081931",
  "fullDetails": {
    "licenseNumber": "12081931",
    "name": "INSTANT PLUMBING",
    "address": "3625 6 ST NE",
    "city": "Calgary",
    "province": "AB",
    "postalCode": "",
    "type": "CONTRACTOR",
    "licenseTypes": "CONTRACTOR",
    "status": "active",
    "issuedDate": "2015-12-01T05:30:46.000Z",
    "expiryDate": "2026-11-30T05:30:46.000Z",
    "coordinates": [
      -114.0486169,
      51.084364
    ],
    "longitude": -114.0486169,
    "latitude": 51.084364,
    "community": "GREENVIEW INDUSTRIAL PARK",
    "ward": "GRI",
    "contacts": {},
    "businessArea": null,
    "estimatedRent": null,
    "buildingType": null,
    "nearbyBusinesses": [],
    "competitorCount": {
      "radius500m": 0,
      "radius1km": 0,
      "radius2km": 0
    },
    "photos": [],
    "notes": ""
  }
}