{
  "id": "12193249",
  "fullDetails": {
    "licenseNumber": "12193249",
    "name": "ALOFT CALGARY UNIVERSITY",
    "address": "2359 BANFF TR NW",
    "city": "Calgary",
    "province": "AB",
    "postalCode": "",
    "type": "AMUSEMENT ARCADE",
    "subType": "ENTERTAINMENT ESTABLISHMENT,",
    "licenseTypes": "AMUSEMENT ARCADE,\nENTERTAINMENT ESTABLISHMENT,\nPERSONAL SERVICE,\nHOTEL/MOTEL,\nALCOHOL BEVERAGE SALES (DRINKING EST/RESTAURANT),\nFOOD SERVICE - PREMISES (SEATING),\nBODY RUB CENTRE (GRANDFATHERED MASSAGE CENTRE COMMERCIAL)",
    "status": "active",
    "issuedDate": "2003-05-30T10:41:09.000Z",
    "expiryDate": "2026-05-29T10:41:09.000Z",
    "coordinates": [
      -114.1152628,
      51.0690781
    ],
    "longitude": -114.1152628,
    "latitude": 51.0690781,
    "community": "BANFF TRAIL",
    "ward": "BNF",
    "contacts": {},
    "businessArea": null,
    "estimatedRent": null,
    "buildingType": null,
    "nearbyBusinesses": [],
    "competitorCount": {
      "radius500m": 0,
      "radius1km": 0,
      "radius2km": 0
    },
    "photos": [],
    "notes": ""
  }
}