{
  "id": "12456091",
  "fullDetails": {
    "licenseNumber": "12456091",
    "name": "HOME DEPOT #7076",
    "address": "11320 SARCEE TR NW",
    "city": "Calgary",
    "province": "AB",
    "postalCode": "",
    "type": "RETAIL DEALER - PREMISES",
    "subType": "ALARM AGENCY,",
    "licenseTypes": "RETAIL DEALER - PREMISES,\nALARM AGENCY,\nFOOD SERVICE - PREMISES,\nCONTRACTOR",
    "status": "pending",
    "issuedDate": "2006-04-05T08:31:05.000Z",
    "expiryDate": "2026-04-04T08:31:05.000Z",
    "coordinates": [
      -114.1611464,
      51.1546061
    ],
    "longitude": -114.1611464,
    "latitude": 51.1546061,
    "community": "SHERWOOD",
    "ward": "SHW",
    "contacts": {},
    "businessArea": null,
    "estimatedRent": null,
    "buildingType": null,
    "nearbyBusinesses": [],
    "competitorCount": {
      "radius500m": 0,
      "radius1km": 0,
      "radius2km": 0
    },
    "photos": [],
    "notes": ""
  }
}