{
  "id": "12722336",
  "fullDetails": {
    "licenseNumber": "12722336",
    "name": "ESSEX LEASE FINANCIAL",
    "address": "10768 74 ST SE",
    "city": "Calgary",
    "province": "AB",
    "postalCode": "",
    "type": "MOTOR VEHICLE DEALER - PREMISES",
    "licenseTypes": "MOTOR VEHICLE DEALER - PREMISES",
    "status": "active",
    "issuedDate": "2025-09-23T10:00:17.000Z",
    "expiryDate": "2026-09-22T10:00:16.000Z",
    "coordinates": [
      -113.9238926,
      50.9592134
    ],
    "longitude": -113.9238926,
    "latitude": 50.9592134,
    "community": "EAST SHEPARD INDUSTRIAL",
    "ward": "ESH",
    "contacts": {},
    "businessArea": null,
    "estimatedRent": null,
    "buildingType": null,
    "nearbyBusinesses": [],
    "competitorCount": {
      "radius500m": 0,
      "radius1km": 0,
      "radius2km": 0
    },
    "photos": [],
    "notes": ""
  }
}