{
  "id": "13151147",
  "fullDetails": {
    "licenseNumber": "13151147",
    "name": "MINHAS FURNITURE (FLAIR DESIGN)",
    "address": "3916 72 AV SE",
    "city": "Calgary",
    "province": "AB",
    "postalCode": "",
    "type": "MANUFACTURER",
    "subType": "WHOLESALER",
    "licenseTypes": "MANUFACTURER,\nWHOLESALER",
    "status": "active",
    "issuedDate": "2014-09-09T05:33:38.000Z",
    "expiryDate": "2026-09-08T05:33:38.000Z",
    "coordinates": [
      -113.9782236,
      50.9904276
    ],
    "longitude": -113.9782236,
    "latitude": 50.9904276,
    "community": "FOOTHILLS",
    "ward": "FHI",
    "contacts": {},
    "businessArea": null,
    "estimatedRent": null,
    "buildingType": null,
    "nearbyBusinesses": [],
    "competitorCount": {
      "radius500m": 0,
      "radius1km": 0,
      "radius2km": 0
    },
    "photos": [],
    "notes": ""
  }
}