{
  "id": "13499421",
  "fullDetails": {
    "licenseNumber": "13499421",
    "name": "LENS FACTORY OPTICAL",
    "address": "#15 4604 37 ST SW",
    "city": "Calgary",
    "province": "AB",
    "postalCode": "",
    "type": "RETAIL DEALER - PREMISES",
    "licenseTypes": "RETAIL DEALER - PREMISES",
    "status": "active",
    "issuedDate": "2012-11-29T12:28:55.000Z",
    "expiryDate": "2026-11-28T12:28:55.000Z",
    "coordinates": [
      -114.1402675,
      51.0139862
    ],
    "longitude": -114.1402675,
    "latitude": 51.0139862,
    "community": "RUTLAND PARK",
    "ward": "RUT",
    "contacts": {},
    "businessArea": null,
    "estimatedRent": null,
    "buildingType": null,
    "nearbyBusinesses": [],
    "competitorCount": {
      "radius500m": 0,
      "radius1km": 0,
      "radius2km": 0
    },
    "photos": [],
    "notes": ""
  }
}