{
  "id": "13576244",
  "fullDetails": {
    "licenseNumber": "13576244",
    "name": "VIETNAM SUB & GRILL",
    "address": "#18 10 COUNTRY HILLS LD NW",
    "city": "Calgary",
    "province": "AB",
    "postalCode": "",
    "type": "FOOD SERVICE - PREMISES (SEATING)",
    "licenseTypes": "FOOD SERVICE - PREMISES (SEATING)",
    "status": "active",
    "issuedDate": "2012-10-31T14:44:55.000Z",
    "expiryDate": "2026-10-30T14:44:55.000Z",
    "coordinates": [
      -114.0723047,
      51.1429023
    ],
    "longitude": -114.0723047,
    "latitude": 51.1429023,
    "community": "COUNTRY HILLS",
    "ward": "COU",
    "contacts": {},
    "businessArea": null,
    "estimatedRent": null,
    "buildingType": null,
    "nearbyBusinesses": [],
    "competitorCount": {
      "radius500m": 0,
      "radius1km": 0,
      "radius2km": 0
    },
    "photos": [],
    "notes": ""
  }
}