{
  "id": "13869466",
  "fullDetails": {
    "licenseNumber": "13869466",
    "name": "RICKY'S ALL DAY GRILL",
    "address": "#14 252 AVIATION BV NE",
    "city": "Calgary",
    "province": "AB",
    "postalCode": "",
    "type": "RETAIL DEALER - PREMISES",
    "subType": "ALCOHOL BEVERAGE SALES (DRINKING EST/RESTAURANT),",
    "licenseTypes": "RETAIL DEALER - PREMISES,\nALCOHOL BEVERAGE SALES (DRINKING EST/RESTAURANT),\nFOOD SERVICE - PREMISES (SEATING),\nOUTDOOR PATIO",
    "status": "active",
    "issuedDate": "2014-11-25T11:49:18.000Z",
    "expiryDate": "2026-11-24T11:49:18.000Z",
    "coordinates": [
      -114.0317449,
      51.0974528
    ],
    "longitude": -114.0317449,
    "latitude": 51.0974528,
    "community": "CALGARY INTERNATIONAL AIRPORT",
    "ward": "CIA",
    "contacts": {},
    "businessArea": null,
    "estimatedRent": null,
    "buildingType": null,
    "nearbyBusinesses": [],
    "competitorCount": {
      "radius500m": 0,
      "radius1km": 0,
      "radius2km": 0
    },
    "photos": [],
    "notes": ""
  }
}