{
  "id": "13892211",
  "fullDetails": {
    "licenseNumber": "13892211",
    "name": "RE-MATT",
    "address": "3234 9 ST SE",
    "city": "Calgary",
    "province": "AB",
    "postalCode": "",
    "type": "SALVAGE YARD/AUTO WRECKER",
    "licenseTypes": "SALVAGE YARD/AUTO WRECKER",
    "status": "active",
    "issuedDate": "2015-01-21T10:36:52.000Z",
    "expiryDate": "2027-01-20T10:36:52.000Z",
    "coordinates": [
      -114.0397312,
      51.0250175
    ],
    "longitude": -114.0397312,
    "latitude": 51.0250175,
    "community": "HIGHFIELD",
    "ward": "HIF",
    "contacts": {},
    "businessArea": null,
    "estimatedRent": null,
    "buildingType": null,
    "nearbyBusinesses": [],
    "competitorCount": {
      "radius500m": 0,
      "radius1km": 0,
      "radius2km": 0
    },
    "photos": [],
    "notes": ""
  }
}