{
  "id": "14917579",
  "fullDetails": {
    "licenseNumber": "14917579",
    "name": "COBRA SEE SNAKE & INSPECTIONS",
    "address": "#10 11410 27 ST SE",
    "city": "Calgary",
    "province": "AB",
    "postalCode": "",
    "type": "MANUFACTURER",
    "licenseTypes": "MANUFACTURER",
    "status": "active",
    "issuedDate": "2021-05-06T13:05:54.000Z",
    "expiryDate": "2026-05-05T13:05:54.000Z",
    "coordinates": [
      -113.9943968,
      50.9536982
    ],
    "longitude": -113.9943968,
    "latitude": 50.9536982,
    "community": "SHEPARD INDUSTRIAL",
    "ward": "SHI",
    "contacts": {},
    "businessArea": null,
    "estimatedRent": null,
    "buildingType": null,
    "nearbyBusinesses": [],
    "competitorCount": {
      "radius500m": 0,
      "radius1km": 0,
      "radius2km": 0
    },
    "photos": [],
    "notes": ""
  }
}