{
  "id": "15087554",
  "fullDetails": {
    "licenseNumber": "15087554",
    "name": "MCKNIGHT 24 HOUR VETERINARY HOSPITAL",
    "address": "#34 5010 4 ST NE",
    "city": "Calgary",
    "province": "AB",
    "postalCode": "",
    "type": "RETAIL DEALER - PREMISES",
    "licenseTypes": "RETAIL DEALER - PREMISES",
    "status": "active",
    "issuedDate": "2018-10-19T15:26:05.000Z",
    "expiryDate": "2026-10-18T15:26:05.000Z",
    "coordinates": [
      -114.0530058,
      51.0972932
    ],
    "longitude": -114.0530058,
    "latitude": 51.0972932,
    "community": "SKYLINE WEST",
    "ward": "SKW",
    "contacts": {},
    "businessArea": null,
    "estimatedRent": null,
    "buildingType": null,
    "nearbyBusinesses": [],
    "competitorCount": {
      "radius500m": 0,
      "radius1km": 0,
      "radius2km": 0
    },
    "photos": [],
    "notes": ""
  }
}