{
  "id": "15105554",
  "fullDetails": {
    "licenseNumber": "15105554",
    "name": "FWS",
    "address": "#1500 840 7 AV SW",
    "city": "Calgary",
    "province": "AB",
    "postalCode": "",
    "type": "CONTRACTOR (NO PROVINCIAL LICENCE REQUIRED)",
    "licenseTypes": "CONTRACTOR (NO PROVINCIAL LICENCE REQUIRED)",
    "status": "active",
    "issuedDate": "2022-09-12T07:50:59.000Z",
    "expiryDate": "2026-09-11T07:50:59.000Z",
    "coordinates": [
      -114.0800452,
      51.0472611
    ],
    "longitude": -114.0800452,
    "latitude": 51.0472611,
    "community": "DOWNTOWN COMMERCIAL CORE",
    "ward": "DNC",
    "contacts": {},
    "businessArea": null,
    "estimatedRent": null,
    "buildingType": null,
    "nearbyBusinesses": [],
    "competitorCount": {
      "radius500m": 0,
      "radius1km": 0,
      "radius2km": 0
    },
    "photos": [],
    "notes": ""
  }
}