{
  "id": "15699069",
  "fullDetails": {
    "licenseNumber": "15699069",
    "name": "RGO FLOORING",
    "address": "#100 229 33 ST NE",
    "city": "Calgary",
    "province": "AB",
    "postalCode": "",
    "type": "WHOLESALER",
    "subType": "CONTRACTOR",
    "licenseTypes": "WHOLESALER,\nCONTRACTOR",
    "status": "active",
    "issuedDate": "2019-11-22T09:43:47.000Z",
    "expiryDate": "2026-11-21T09:43:47.000Z",
    "coordinates": [
      -113.9877357,
      51.0526663
    ],
    "longitude": -113.9877357,
    "latitude": 51.0526663,
    "community": "FRANKLIN",
    "ward": "FRA",
    "contacts": {},
    "businessArea": null,
    "estimatedRent": null,
    "buildingType": null,
    "nearbyBusinesses": [],
    "competitorCount": {
      "radius500m": 0,
      "radius1km": 0,
      "radius2km": 0
    },
    "photos": [],
    "notes": ""
  }
}