{
  "id": "15709298",
  "fullDetails": {
    "licenseNumber": "15709298",
    "name": "CADENT MILLINGS CENTRE",
    "address": "#1 4015 1 ST SE",
    "city": "Calgary",
    "province": "AB",
    "postalCode": "",
    "type": "MANUFACTURER",
    "licenseTypes": "MANUFACTURER",
    "status": "active",
    "issuedDate": "2020-06-22T16:24:44.000Z",
    "expiryDate": "2026-06-21T16:24:44.000Z",
    "coordinates": [
      -114.0599347,
      51.0175061
    ],
    "longitude": -114.0599347,
    "latitude": 51.0175061,
    "community": "MANCHESTER INDUSTRIAL",
    "ward": "MNI",
    "contacts": {},
    "businessArea": null,
    "estimatedRent": null,
    "buildingType": null,
    "nearbyBusinesses": [],
    "competitorCount": {
      "radius500m": 0,
      "radius1km": 0,
      "radius2km": 0
    },
    "photos": [],
    "notes": ""
  }
}