{
  "id": "15890072",
  "fullDetails": {
    "licenseNumber": "15890072",
    "name": "STARLITE RESTAURANT AND BAR",
    "address": "369 HERITAGE DR SE",
    "city": "Calgary",
    "province": "AB",
    "postalCode": "",
    "type": "ALCOHOL BEVERAGE SALES (DRINKING EST/RESTAURANT)",
    "subType": "FOOD SERVICE - PREMISES (SEATING)",
    "licenseTypes": "ALCOHOL BEVERAGE SALES (DRINKING EST/RESTAURANT),\nFOOD SERVICE - PREMISES (SEATING)",
    "status": "active",
    "issuedDate": "2020-06-29T15:23:10.000Z",
    "expiryDate": "2026-06-28T15:23:10.000Z",
    "coordinates": [
      -114.0614356,
      50.978553
    ],
    "longitude": -114.0614356,
    "latitude": 50.978553,
    "community": "ACADIA",
    "ward": "ACA",
    "contacts": {},
    "businessArea": null,
    "estimatedRent": null,
    "buildingType": null,
    "nearbyBusinesses": [],
    "competitorCount": {
      "radius500m": 0,
      "radius1km": 0,
      "radius2km": 0
    },
    "photos": [],
    "notes": ""
  }
}