{
  "id": "15921141",
  "fullDetails": {
    "licenseNumber": "15921141",
    "name": "MGI AUTO",
    "address": "3514E 73 AV SE",
    "city": "Calgary",
    "province": "AB",
    "postalCode": "",
    "type": "MOTOR VEHICLE DEALER - PREMISES",
    "subType": "MOTOR VEHICLE REPAIR AND SERVICE (1)",
    "licenseTypes": "MOTOR VEHICLE DEALER - PREMISES,\nMOTOR VEHICLE REPAIR AND SERVICE (1)",
    "status": "active",
    "issuedDate": "2021-05-11T13:27:28.000Z",
    "expiryDate": "2026-05-10T13:27:28.000Z",
    "coordinates": [
      -113.9828551,
      50.9886819
    ],
    "longitude": -113.9828551,
    "latitude": 50.9886819,
    "community": "FOOTHILLS",
    "ward": "FHI",
    "contacts": {},
    "businessArea": null,
    "estimatedRent": null,
    "buildingType": null,
    "nearbyBusinesses": [],
    "competitorCount": {
      "radius500m": 0,
      "radius1km": 0,
      "radius2km": 0
    },
    "photos": [],
    "notes": ""
  }
}