{
  "id": "16101206",
  "fullDetails": {
    "licenseNumber": "16101206",
    "name": "OSCAR WYLEE PTY",
    "address": "#L2 3625 SHAGANAPPI TR NW",
    "city": "Calgary",
    "province": "AB",
    "postalCode": "",
    "type": "RETAIL DEALER - PREMISES",
    "licenseTypes": "RETAIL DEALER - PREMISES",
    "status": "active",
    "issuedDate": "2022-01-05T16:50:39.000Z",
    "expiryDate": "2027-01-04T16:50:39.000Z",
    "coordinates": [
      -114.1544514,
      51.0851295
    ],
    "longitude": -114.1544514,
    "latitude": 51.0851295,
    "community": "VARSITY",
    "ward": "VAR",
    "contacts": {},
    "businessArea": null,
    "estimatedRent": null,
    "buildingType": null,
    "nearbyBusinesses": [],
    "competitorCount": {
      "radius500m": 0,
      "radius1km": 0,
      "radius2km": 0
    },
    "photos": [],
    "notes": ""
  }
}