{
  "id": "161158",
  "fullDetails": {
    "licenseNumber": "161158",
    "name": "L A D'S AUTO REPAIR",
    "address": "3832 16 ST SE",
    "city": "Calgary",
    "province": "AB",
    "postalCode": "",
    "type": "MOTOR VEHICLE REPAIR AND SERVICE (1)",
    "licenseTypes": "MOTOR VEHICLE REPAIR AND SERVICE (1)",
    "status": "active",
    "issuedDate": "2001-06-01T00:00:00.000Z",
    "expiryDate": "2026-12-31T00:00:00.000Z",
    "coordinates": [
      -114.0217621,
      51.020577
    ],
    "longitude": -114.0217621,
    "latitude": 51.020577,
    "community": "ALYTH/BONNYBROOK",
    "ward": "AYB",
    "contacts": {},
    "businessArea": null,
    "estimatedRent": null,
    "buildingType": null,
    "nearbyBusinesses": [],
    "competitorCount": {
      "radius500m": 0,
      "radius1km": 0,
      "radius2km": 0
    },
    "photos": [],
    "notes": ""
  }
}