{
  "id": "16349086",
  "fullDetails": {
    "licenseNumber": "16349086",
    "name": "YYC LASER & SKINCARE",
    "address": "#109H 1526 9 AV SE",
    "city": "Calgary",
    "province": "AB",
    "postalCode": "",
    "type": "PERSONAL SERVICE",
    "licenseTypes": "PERSONAL SERVICE",
    "status": "active",
    "issuedDate": "2024-07-22T10:24:03.000Z",
    "expiryDate": "2026-07-21T10:24:02.000Z",
    "coordinates": [
      -114.0271973,
      51.0387734
    ],
    "longitude": -114.0271973,
    "latitude": 51.0387734,
    "community": "INGLEWOOD",
    "ward": "ING",
    "contacts": {},
    "businessArea": null,
    "estimatedRent": null,
    "buildingType": null,
    "nearbyBusinesses": [],
    "competitorCount": {
      "radius500m": 0,
      "radius1km": 0,
      "radius2km": 0
    },
    "photos": [],
    "notes": ""
  }
}