{
  "id": "16447237",
  "fullDetails": {
    "licenseNumber": "16447237",
    "name": "LAGREE YYC",
    "address": "3105 MCCAIG ST NW",
    "city": "Calgary",
    "province": "AB",
    "postalCode": "",
    "type": "RETAIL DEALER - PREMISES",
    "subType": "PERSONAL SERVICE (FITNESS CONDITIONING)",
    "licenseTypes": "RETAIL DEALER - PREMISES,\nPERSONAL SERVICE (FITNESS CONDITIONING)",
    "status": "active",
    "issuedDate": "2024-07-12T10:59:12.000Z",
    "expiryDate": "2026-07-11T10:59:11.000Z",
    "coordinates": [
      -114.1432049,
      51.0787547
    ],
    "longitude": -114.1432049,
    "latitude": 51.0787547,
    "community": "UNIVERSITY DISTRICT",
    "ward": "UND",
    "contacts": {},
    "businessArea": null,
    "estimatedRent": null,
    "buildingType": null,
    "nearbyBusinesses": [],
    "competitorCount": {
      "radius500m": 0,
      "radius1km": 0,
      "radius2km": 0
    },
    "photos": [],
    "notes": ""
  }
}