{
  "id": "16467102",
  "fullDetails": {
    "licenseNumber": "16467102",
    "name": "COMBINA GLOBAL",
    "address": "#207 4616 VALIANT DR NW",
    "city": "Calgary",
    "province": "AB",
    "postalCode": "",
    "type": "WHOLESALER",
    "subType": "CONTRACTOR",
    "licenseTypes": "WHOLESALER,\nCONTRACTOR",
    "status": "active",
    "issuedDate": "2024-05-21T12:55:39.000Z",
    "expiryDate": "2026-05-20T12:55:39.000Z",
    "coordinates": [
      -114.1532646,
      51.0913435
    ],
    "longitude": -114.1532646,
    "latitude": 51.0913435,
    "community": "VARSITY",
    "ward": "VAR",
    "contacts": {},
    "businessArea": null,
    "estimatedRent": null,
    "buildingType": null,
    "nearbyBusinesses": [],
    "competitorCount": {
      "radius500m": 0,
      "radius1km": 0,
      "radius2km": 0
    },
    "photos": [],
    "notes": ""
  }
}