{
  "id": "16482986",
  "fullDetails": {
    "licenseNumber": "16482986",
    "name": "PAINTSBYEM",
    "address": "#314 4620 BOW TR SW",
    "city": "Calgary",
    "province": "AB",
    "postalCode": "",
    "type": "PERSONAL SERVICE",
    "subType": "RETAIL DEALER - PREMISES",
    "licenseTypes": "PERSONAL SERVICE,\nRETAIL DEALER - PREMISES",
    "status": "active",
    "issuedDate": "2024-12-10T08:01:29.000Z",
    "expiryDate": "2026-12-09T08:01:29.000Z",
    "coordinates": [
      -114.1531297,
      51.049158
    ],
    "longitude": -114.1531297,
    "latitude": 51.049158,
    "community": "WILDWOOD",
    "ward": "WLD",
    "contacts": {},
    "businessArea": null,
    "estimatedRent": null,
    "buildingType": null,
    "nearbyBusinesses": [],
    "competitorCount": {
      "radius500m": 0,
      "radius1km": 0,
      "radius2km": 0
    },
    "photos": [],
    "notes": ""
  }
}