{
  "id": "16587552",
  "fullDetails": {
    "licenseNumber": "16587552",
    "name": "RAYS AUTO SERVICE",
    "address": "#2 2020 35 AV NE",
    "city": "Calgary",
    "province": "AB",
    "postalCode": "",
    "type": "RETAIL DEALER - PREMISES",
    "subType": "MOTOR VEHICLE REPAIR AND SERVICE (1)",
    "licenseTypes": "RETAIL DEALER - PREMISES,\nMOTOR VEHICLE REPAIR AND SERVICE (1)",
    "status": "pending",
    "issuedDate": "2025-03-19T11:30:27.000Z",
    "expiryDate": "2026-03-18T11:30:26.000Z",
    "coordinates": [
      -114.010314,
      51.0842698
    ],
    "longitude": -114.010314,
    "latitude": 51.0842698,
    "community": "NORTH AIRWAYS",
    "ward": "NAW",
    "contacts": {},
    "businessArea": null,
    "estimatedRent": null,
    "buildingType": null,
    "nearbyBusinesses": [],
    "competitorCount": {
      "radius500m": 0,
      "radius1km": 0,
      "radius2km": 0
    },
    "photos": [],
    "notes": ""
  }
}