{
  "id": "16618043",
  "fullDetails": {
    "licenseNumber": "16618043",
    "name": "MELANIE LYNE",
    "address": "#E17 3625 SHAGANAPPI TR NW",
    "city": "Calgary",
    "province": "AB",
    "postalCode": "",
    "type": "RETAIL DEALER - PREMISES",
    "licenseTypes": "RETAIL DEALER - PREMISES",
    "status": "active",
    "issuedDate": "2025-05-09T13:15:12.000Z",
    "expiryDate": "2026-05-08T13:15:10.000Z",
    "coordinates": [
      -114.1548077,
      51.0851531
    ],
    "longitude": -114.1548077,
    "latitude": 51.0851531,
    "community": "VARSITY",
    "ward": "VAR",
    "contacts": {},
    "businessArea": null,
    "estimatedRent": null,
    "buildingType": null,
    "nearbyBusinesses": [],
    "competitorCount": {
      "radius500m": 0,
      "radius1km": 0,
      "radius2km": 0
    },
    "photos": [],
    "notes": ""
  }
}