{
  "id": "19588",
  "fullDetails": {
    "licenseNumber": "19588",
    "name": "SOUTH WEST VACUUMS",
    "address": "1910 37 ST SW",
    "city": "Calgary",
    "province": "AB",
    "postalCode": "",
    "type": "RETAIL DEALER - PREMISES",
    "subType": "SECONDHAND DEALER",
    "licenseTypes": "RETAIL DEALER - PREMISES,\nSECONDHAND DEALER",
    "status": "active",
    "issuedDate": "2001-06-01T00:00:00.000Z",
    "expiryDate": "2027-02-14T05:31:23.000Z",
    "coordinates": [
      -114.1408404,
      51.0375761
    ],
    "longitude": -114.1408404,
    "latitude": 51.0375761,
    "community": "KILLARNEY/GLENGARRY",
    "ward": "KIL",
    "contacts": {},
    "businessArea": null,
    "estimatedRent": null,
    "buildingType": null,
    "nearbyBusinesses": [],
    "competitorCount": {
      "radius500m": 0,
      "radius1km": 0,
      "radius2km": 0
    },
    "photos": [],
    "notes": ""
  }
}