{
  "id": "198234",
  "fullDetails": {
    "licenseNumber": "198234",
    "name": "CASTLE MAINTENANCE SERVICES",
    "address": "#147 2432 48 ST SE",
    "city": "Calgary",
    "province": "AB",
    "postalCode": "",
    "type": "CLEANING SERVICE (COMMERCIAL & RESIDENTIAL)",
    "subType": "CONTRACTOR",
    "licenseTypes": "CLEANING SERVICE (COMMERCIAL & RESIDENTIAL),\nCONTRACTOR",
    "status": "active",
    "issuedDate": "2001-06-01T00:00:00.000Z",
    "expiryDate": "2026-07-09T17:43:59.000Z",
    "coordinates": [
      -113.9630074,
      51.031856
    ],
    "longitude": -113.9630074,
    "latitude": 51.031856,
    "community": "FOREST LAWN INDUSTRIAL",
    "ward": "FLI",
    "contacts": {},
    "businessArea": null,
    "estimatedRent": null,
    "buildingType": null,
    "nearbyBusinesses": [],
    "competitorCount": {
      "radius500m": 0,
      "radius1km": 0,
      "radius2km": 0
    },
    "photos": [],
    "notes": ""
  }
}