{
  "id": "411587",
  "fullDetails": {
    "licenseNumber": "411587",
    "name": "FINISHING TRADITIONS",
    "address": "4536 14 ST NE",
    "city": "Calgary",
    "province": "AB",
    "postalCode": "",
    "type": "FURNITURE REFINISHING",
    "licenseTypes": "FURNITURE REFINISHING",
    "status": "active",
    "issuedDate": "2001-06-01T00:00:00.000Z",
    "expiryDate": "2026-12-14T00:00:00.000Z",
    "coordinates": [
      -114.0266584,
      51.0926796
    ],
    "longitude": -114.0266584,
    "latitude": 51.0926796,
    "community": "MCCALL",
    "ward": "MCI",
    "contacts": {},
    "businessArea": null,
    "estimatedRent": null,
    "buildingType": null,
    "nearbyBusinesses": [],
    "competitorCount": {
      "radius500m": 0,
      "radius1km": 0,
      "radius2km": 0
    },
    "photos": [],
    "notes": ""
  }
}