{
  "id": "777649",
  "fullDetails": {
    "licenseNumber": "777649",
    "name": "MAC'S CONVENIENCE STORE #2113",
    "address": "1904 19 ST NE",
    "city": "Calgary",
    "province": "AB",
    "postalCode": "",
    "type": "TOBACCO RETAILER",
    "subType": "RETAIL DEALER - PREMISES,",
    "licenseTypes": "TOBACCO RETAILER,\nRETAIL DEALER - PREMISES,\nFOOD SERVICE - PREMISES,\nVAPE RETAILER",
    "status": "active",
    "issuedDate": "2005-06-21T08:32:47.000Z",
    "expiryDate": "2026-06-20T08:32:47.000Z",
    "coordinates": [
      -114.0129417,
      51.0693712
    ],
    "longitude": -114.0129417,
    "latitude": 51.0693712,
    "community": "VISTA HEIGHTS",
    "ward": "VIS",
    "contacts": {},
    "businessArea": null,
    "estimatedRent": null,
    "buildingType": null,
    "nearbyBusinesses": [],
    "competitorCount": {
      "radius500m": 0,
      "radius1km": 0,
      "radius2km": 0
    },
    "photos": [],
    "notes": ""
  }
}