{
  "id": "856898",
  "fullDetails": {
    "licenseNumber": "856898",
    "name": "TOTAL IMAGE INTERIORS",
    "address": "7012 FISHER RD SE",
    "city": "Calgary",
    "province": "AB",
    "postalCode": "",
    "type": "WHOLESALER",
    "subType": "CONTRACTOR",
    "licenseTypes": "WHOLESALER,\nCONTRACTOR",
    "status": "active",
    "issuedDate": "2018-10-24T05:32:50.000Z",
    "expiryDate": "2026-10-23T05:32:50.000Z",
    "coordinates": [
      -114.0674465,
      50.9917769
    ],
    "longitude": -114.0674465,
    "latitude": 50.9917769,
    "community": "FAIRVIEW INDUSTRIAL",
    "ward": "FVI",
    "contacts": {},
    "businessArea": null,
    "estimatedRent": null,
    "buildingType": null,
    "nearbyBusinesses": [],
    "competitorCount": {
      "radius500m": 0,
      "radius1km": 0,
      "radius2km": 0
    },
    "photos": [],
    "notes": ""
  }
}